tau_upperlimitstools_fitting/__init__.py
tau_upperlimitstools_fitting/functions_fit.py
tau_upperlimitstools_fitting/functions_ul.py
tau_upperlimitstools_fitting/utility.py
tau_upperlimitstools_fitting-1.1.dist-info/METADATA
tau_upperlimitstools_fitting-1.1.dist-info/WHEEL
tau_upperlimitstools_fitting-1.1.dist-info/licenses/LICENSE
tau_upperlimitstools_fitting-1.1.dist-info/RECORD
