Metadata-Version: 2.1
Name: tau_upperlimitstools_fitting
Version: 1.1
Summary: Tau_upperlimitstools_fitting based on ROOT.
Project-URL: Homepage, https://gitlab.desy.de/belle2/physics/tau/tau_upperlimitstools_fitting
Author-email: Marcela Garcia <mgarciah@post.kek.jp>
License-File: LICENSE
Classifier: License :: OSI Approved :: MIT License
Classifier: Operating System :: OS Independent
Classifier: Programming Language :: Python :: 3
Requires-Python: >=3.8
